{
  "BouncyJello": {
    "bestScore": 374779,
    "timestamp": "2024-09-25T18:27:58.119Z"
  },
  "Valoutrix": {
    "bestScore": 161004,
    "timestamp": "2024-09-25T18:28:40.148Z"
  },
  "snow_leopard": {
    "bestScore": 35697,
    "timestamp": "2024-09-25T18:15:40.329Z"
  },
  "Dxedalus": {
    "bestScore": 19826,
    "timestamp": "2024-09-25T18:15:40.330Z"
  },
  "Jamiemac": {
    "bestScore": 3545,
    "timestamp": "2024-09-25T18:15:40.330Z"
  },
  "Avel": {
    "bestScore": 41,
    "timestamp": "2024-09-25T18:15:40.330Z"
  }
}